fs_transaction/__init__.py
fs_transaction/actions.py
fs_transaction/core.py
fs_transaction-0.1.1.dist-info/licenses/LICENSE
fs_transaction-0.1.1.dist-info/METADATA
fs_transaction-0.1.1.dist-info/WHEEL
fs_transaction-0.1.1.dist-info/top_level.txt
fs_transaction-0.1.1.dist-info/RECORD
