Metadata-Version: 2.4
Name: fs-transaction
Version: 0.1.1
Summary: Atomic filesystem operations for safe batch processing.
Author-email: Sarath Kaul <kaul.sarath@gmail.com>
Project-URL: Homepage, https://github.com/SKAUL05/fs-transaction
Project-URL: Bug Tracker, https://github.com/SKAUL05/fs-transaction/issues
Classifier: Programming Language :: Python :: 3
Classifier: License :: OSI Approved :: MIT License
Classifier: Operating System :: OS Independent
Requires-Python: >=3.7
License-File: LICENSE
Dynamic: license-file
